{
    "Suits": {
        "0": {
            "cost": 400,
            "name": "RX-78 Gundam",
            "pilots": {
                "0": "Amuro Ray",
                "1": "Ryu Jose"
            },
            "shooting": {
                "1": {
                    "type": "Main",
                    "name": "Beam Rifle",
                    "ammo": "7",
                    "damage": "70",
                    "cancels": "AB,AC,BC",
                    "vernier": "No",
                    "notes": "Over-the-shoulder shot when facing away"
                },
                "2": {
                    "type": "Sub Weapon",
                    "name": "Hyper Bazooka",
                    "ammo": "3",
                    "damage": "99",
                    "cancels": "AC",
                    "vernier": "Yes",
                    "notes": ""
                },
                "3": {
                    "type": "Special Shooting",
                    "name": "Beam Javelin",
                    "ammo": "-",
                    "damage": "90-140-190",
                    "cancels": "-",
                    "vernier": "Yes",
                    "notes": "Hold input to charge"
                },
                "4": {
                    "type": "Special Melee",
                    "name": "Gundam Hammer",
                    "ammo": "-",
                    "damage": "24 to 114",
                    "cancels": "-",
                    "vernier": "Yes",
                    "notes": "Multi hit"
                },
                "5": {
                    "type": "Charge Shot A",
                    "name": "Beam Rifle(Sniper)",
                    "ammo": "-",
                    "damage": "120",
                    "cancels": "-",
                    "vernier": "Yes",
                    "notes": "High Velocity"
                }
            },
            "Fighting": {
                "Neutral Melee": {
                    "1": {
                        "Name": "Beam Saber",
                        "Input": "BBB",
                        "Damage": "173",
                        "Routes": "BC(1-2nd hit)",
                        "Steppable": "yes",
                        "Notes": ""
                    },
                    "2": {
                        "Name": "Beam Saber",
                        "Input": "BB(8)BB",
                        "Damage": "215",
                        "Routes": "BC(1-3rd hit)",
                        "Steppable": "yes",
                        "Notes": ""
                    }
                },
                "Forward Melee": {
                    "1": {
                        "Name": "Beam Saber Puncture",
                        "Input": "8B",
                        "Damage": "84",
                        "Routes": "BC",
                        "Steppable": "yes",
                        "Notes": ""
                    }
                },
                "Side Melee": {
                    "1": {
                        "Name": "Gundam Hammer",
                        "Input": "6BB",
                        "Damage": "154",
                        "Routes": "BC(1-2nd hit)",
                        "Steppable": "yes",
                        "Notes": "Wide swing, beside and behind"
                    }
                },
                "Back Melee": {
                    "1": {
                        "Name": "Battle Counter",
                        "Input": "2B",
                        "Damage": "80",
                        "Routes": "-",
                        "Steppable": "yes",
                        "Notes": "Pushes forward after a delay blocking shots"
                    },
                    "2": {
                        "Name": "Shield Throw and Leap",
                        "Input": "2B-A-B",
                        "Damage": "215",
                        "Routes": "55(throw)-135(Leap)",
                        "Steppable": "No",
                        "Notes": "Shield throw will stun, Shield Throw not steppable"
                    }
                },
                "Boost Dash Melee": {
                    "1": {
                        "Name": "Combination attack",
                        "Input": "BD8BBB",
                        "Damage": "190",
                        "Routes": "-",
                        "Notes": ""
                    }
                },
                "Special Fighting": {
                    "1": {
                        "Name": "Stomp",
                        "Input": "BC during melee",
                        "Damage": "147 to 210",
                        "Routes": "-",
                        "Notes": "Usable during most melee, Ground bounces"
                    }
                }
            },
            "Special": {
                "1": {
                    "Name": "Last Shooting",
                    "Input": "ABC",
                    "Damage": "296/274",
                    "Notes": "Two Stage Super, slash then Shot"
                }
            }
        }
    }
}